dotted_dict/__init__.py
dotted_dict-1.1.2.dist-info/METADATA
dotted_dict-1.1.2.dist-info/WHEEL
dotted_dict-1.1.2.dist-info/top_level.txt
dotted_dict-1.1.2.dist-info/RECORD
