Metadata-Version: 1.1
Name: dotted-dict
Version: 1.1.2
Summary: dict object with support for addressing keys in dot notation.
Home-page: https://github.com/josh-paul/dotted_dict
Author: Josh Paul
Author-email: trevalen@me.com
License: Apache v2
Keywords: dotted dict dotted_dict
Platform: UNKNOWN
Classifier: Development Status :: 5 - Production/Stable
Classifier: Intended Audience :: Developers
Classifier: License :: OSI Approved :: Apache Software License
Classifier: Programming Language :: Python
Classifier: Programming Language :: Python :: 2.7
Classifier: Programming Language :: Python :: 3.4
Classifier: Programming Language :: Python :: 3.5
Classifier: Programming Language :: Python :: 3.6
